{
    "id0": {
        "lat": 59.81084701448695,
        "lon": 17.65699901427326,
        "heading": -1,
        "speed": 5,
        "alt": 8.0
    },
    "id1": {
        "lat": 59.80968425716309,
        "lon": 17.656837326106587,
        "heading": -1,
        "speed": 1.0,
        "alt": 8.0
    },
    "id2": {
        "lat": 59.809688494863785,
        "lon": 17.6568916973011,
        "heading": -1,
        "speed": 1.0,
        "alt": 8.0
    },
    "id3": {
        "lat": 59.81085224626001,
        "lon": 17.657053525632282,
        "heading": -1,
        "speed": 1.0,
        "alt": 8.0
    },
    "id4": {
        "lat": 59.8108574780105,
        "lon": 17.657108037008424,
        "heading": -1,
        "speed": 1.0,
        "alt": 8.0
    },
    "id5": {
        "lat": 59.809692732542004,
        "lon": 17.656946068509438,
        "heading": -1,
        "speed": 1.0,
        "alt": 8.0
    },
    "id6": {
        "lat": 59.80969697019786,
        "lon": 17.657000439731597,
        "heading": -1,
        "speed": 1.0,
        "alt": 8.0
    },
    "id7": {
        "lat": 59.810862709738466,
        "lon": 17.65716254840168,
        "heading": -1,
        "speed": 1.0,
        "alt": 8.0
    },
    "id8": {
        "lat": 59.810867941443895,
        "lon": 17.65721705981204,
        "heading": -1,
        "speed": 1.0,
        "alt": 8.0
    },
    "id9": {
        "lat": 59.80970120783124,
        "lon": 17.657054810967583,
        "heading": -1,
        "speed": 1.0,
        "alt": 8.0
    },
    "id10": {
        "lat": 59.809705445442226,
        "lon": 17.657109182217386,
        "heading": -1,
        "speed": 1.0,
        "alt": 8.0
    },
    "id11": {
        "lat": 59.810873173126765,
        "lon": 17.657271571239516,
        "heading": -1,
        "speed": 1.0,
        "alt": 8.0
    }
}